remixt/__init__.py
remixt/_version.py
remixt/bamreader.so
remixt/bpmodel.so
remixt/cn_model.py
remixt/cn_plot.py
remixt/config.py
remixt/defaults.py
remixt/likelihood.py
remixt/ref_data.py
remixt/segalg.py
remixt/seqdataio.py
remixt/utils.py
remixt/visualize.py
remixt/workflow.py
remixt/analysis/__init__.py
remixt/analysis/breakpoints.py
remixt/analysis/experiment.py
remixt/analysis/gcbias.py
remixt/analysis/haplotype.py
remixt/analysis/pipeline.py
remixt/analysis/readcount.py
remixt/analysis/readdepth.py
remixt/analysis/segment.py
remixt/analysis/stats.py
remixt/mappability/__init__.py
remixt/mappability/tasks.py
remixt/mappability/bwa/__init__.py
remixt/mappability/bwa/workflow.py
remixt/simulations/__init__.py
remixt/simulations/balanced.py
remixt/simulations/experiment.py
remixt/simulations/haplotype.py
remixt/simulations/pipeline.py
remixt/simulations/seqread.py
remixt/simulations/simple.py
remixt/simulations/workflow.py
remixt/tests/__init__.py
remixt/tests/test_likelihood.py
remixt/tests/test_model.py
remixt/tests/test_remixt.py
remixt/tests/test_segalg.py
remixt/tests/test_seqdata.py
remixt/tests/utils.py
remixt/tests/unopt/__init__.py
remixt/tests/unopt/model.py
remixt/ui/__init__.py
remixt/ui/create_ref_data.py
remixt/ui/main.py
remixt/ui/mappability_bwa.py
remixt/ui/plot_results.py
remixt/ui/run.py
remixt/ui/visualize_solutions.py
remixt/ui/write_results.py
remixt/wrappers/__init__.py
remixt/wrappers/cmdline.py
remixt/wrappers/utils.py
remixt/wrappers/wrapclonehd.py
remixt/wrappers/wrapremixt.py
remixt/wrappers/wraptheta.py
remixt/wrappers/wraptitan.py
remixt-0.5.6.dist-info/METADATA
remixt-0.5.6.dist-info/RECORD
remixt-0.5.6.dist-info/WHEEL
remixt-0.5.6.dist-info/entry_points.txt
remixt-0.5.6.dist-info/top_level.txt
