Metadata-Version: 2.1
Name: remixt
Version: 0.5.6
Summary: ReMixT is a tool for joint inference of clone specific segment and breakpoint copy number
Home-page: http://bitbucket.org/dranew/remixt
Author: Andrew McPherson
Author-email: andrew.mcpherson@gmail.com
License: UNKNOWN
Download-URL: https://bitbucket.org/dranew/remixt/get/v0.5.6.tar.gz
Keywords: scientific,sequence analysis,cancer
Platform: UNKNOWN
